aprsd_stock_plugin/__init__.py
aprsd_stock_plugin/stock.py
aprsd_stock_plugin-0.1.3.dist-info/LICENSE
aprsd_stock_plugin-0.1.3.dist-info/METADATA
aprsd_stock_plugin-0.1.3.dist-info/WHEEL
aprsd_stock_plugin-0.1.3.dist-info/pbr.json
aprsd_stock_plugin-0.1.3.dist-info/top_level.txt
aprsd_stock_plugin-0.1.3.dist-info/RECORD
