Metadata-Version: 2.1
Name: aprsd-stock-plugin
Version: 0.1.3
Summary: Ham Radio APRSD Plugin for fetching stock quotes
Author: Walter A. Boring IV
Author-email: waboring@hemna.com
License: Apache-2.0
Classifier: Topic :: Communications :: Ham Radio
Classifier: Operating System :: POSIX :: Linux
Classifier: Programming Language :: Python
Classifier: Programming Language :: Python :: 3.7
Classifier: Programming Language :: Python :: 3.8
Classifier: Programming Language :: Python :: 3.9
License-File: LICENSE
Requires-Dist: pbr
Requires-Dist: aprsd (>=2.4.0)
Requires-Dist: yfinance
